memoize.py
setup.cfg
setup.py
memoize2.egg-info/PKG-INFO
memoize2.egg-info/SOURCES.txt
memoize2.egg-info/dependency_links.txt
memoize2.egg-info/top_level.txt