Metadata-Version: 1.0
Name: memoize2
Version: 0.1.1
Summary: The memoize library can be used to quickly add the memoization feature to any existing function so that you can cache previously calculated results for the same arguments but don't have to "clutter" your function code to add the memoization feature into your function.
Home-page: https://github.com/rlgomes/memoize
Author: Rodney Gomes
Author-email: rodneygomes@gmail.com
License: Apache 2.0 License
Keywords: memoize,library
Platform: UNKNOWN
